clitt/__init__.py
clitt/__main__.py
clitt/actions.py
clitt/auth.py
clitt/config/.gitkeep
clitt/config/__init__.py
clitt/config/keys.json
clitt/config/user_keys.json
clitt/enviroment.py
clitt/interface.py
clitt-1.2.1.dist-info/entry_points.txt
clitt-1.2.1.dist-info/LICENSE
clitt-1.2.1.dist-info/WHEEL
clitt-1.2.1.dist-info/METADATA
clitt-1.2.1.dist-info/RECORD
