Metadata-Version: 2.1
Name: clitt
Version: 1.2.1
Summary: Use Twitter from your terminal!
Home-page: https://github.com/leviosar/clitt
Keywords: Twitter,Client,Command-line
Author: Joao Vitor Maia
Author-email: maia.tostring@gmail.com
Requires-Python: >=3.7,<4.0
Classifier: Programming Language :: Python :: 3
Classifier: Programming Language :: Python :: 3.7
Classifier: Programming Language :: Python :: 3.8
Requires-Dist: click (>=7.0,<8.0)
Requires-Dist: colorama (>=0.4.1,<0.5.0)
Requires-Dist: tweepy (>=3.8,<4.0)
Project-URL: Documentation, https://github.com/leviosar/clitt
Project-URL: Repository, https://github.com/leviosar/clitt
